{
  "page": {
    "width_mm": 297,
    "height_mm": 423,
    "unit": "mm",
    "title": "文件准备流程"
  },
  "style": {
    "font": "Microsoft YaHei UI",
    "font_size_pt": 14,
    "theme": "classic_flow",
    "fill": "#FFFFFF",
    "line": "#202020",
    "line_width_pt": 1.2,
    "text_color": "#111111",
    "corner_radius_mm": 1.5
  },
  "nodes": [
    {
      "id": "start",
      "label": "开始\n选择发送内容",
      "shape": "ellipse",
      "x_mm": 104.0,
      "y_mm": 27.0,
      "width_mm": 92,
      "height_mm": 26,
      "fill": "#F4F4F4",
      "layer": "life"
    },
    {
      "id": "collect",
      "label": "收集文件或文件夹",
      "shape": "rounded_rectangle",
      "x_mm": 103.0,
      "y_mm": 78.0,
      "width_mm": 94,
      "height_mm": 34,
      "fill": "#EAF2FF",
      "layer": "ui"
    },
    {
      "id": "folder",
      "label": "文件夹打包",
      "shape": "rounded_rectangle",
      "x_mm": 103.0,
      "y_mm": 133.0,
      "width_mm": 94,
      "height_mm": 34,
      "fill": "#E8F3E8",
      "layer": "backend"
    },
    {
      "id": "type",
      "label": "类型支持?",
      "shape": "diamond",
      "x_mm": 113.0,
      "y_mm": 185.0,
      "width_mm": 74,
      "height_mm": 50,
      "fill": "#FFF3D6",
      "layer": "decision"
    },
    {
      "id": "reject",
      "label": "提示不支持",
      "shape": "rounded_rectangle",
      "x_mm": 198.0,
      "y_mm": 193.0,
      "width_mm": 94,
      "height_mm": 34,
      "fill": "#FCE8E6",
      "layer": "fail"
    },
    {
      "id": "hash",
      "label": "计算大小和SHA",
      "shape": "rounded_rectangle",
      "x_mm": 103.0,
      "y_mm": 253.0,
      "width_mm": 94,
      "height_mm": 34,
      "fill": "#E8F3E8",
      "layer": "backend"
    },
    {
      "id": "source",
      "label": "生成发送源",
      "shape": "rounded_rectangle",
      "x_mm": 103.0,
      "y_mm": 308.0,
      "width_mm": 94,
      "height_mm": 34,
      "fill": "#E8F3E8",
      "layer": "backend"
    },
    {
      "id": "end",
      "label": "准备完成",
      "shape": "ellipse",
      "x_mm": 104.0,
      "y_mm": 367.0,
      "width_mm": 92,
      "height_mm": 26,
      "fill": "#F4F4F4",
      "layer": "life"
    }
  ],
  "edges": [
    {
      "id": "e1",
      "from": "start",
      "to": "collect",
      "arrow": "end",
      "layer": "line"
    },
    {
      "id": "e2",
      "from": "collect",
      "to": "folder",
      "arrow": "end",
      "layer": "line"
    },
    {
      "id": "e3",
      "from": "folder",
      "to": "type",
      "arrow": "end",
      "layer": "line"
    },
    {
      "id": "e4",
      "from": "type",
      "to": "reject",
      "arrow": "end",
      "layer": "line",
      "label": "否"
    },
    {
      "id": "e5",
      "from": "type",
      "to": "hash",
      "arrow": "end",
      "layer": "line",
      "label": "是"
    },
    {
      "id": "e6",
      "from": "hash",
      "to": "source",
      "arrow": "end",
      "layer": "line"
    },
    {
      "id": "e7",
      "from": "source",
      "to": "end",
      "arrow": "end",
      "layer": "line"
    }
  ],
  "groups": [],
  "annotations": [
    {
      "id": "title",
      "text": "文件准备流程",
      "x_mm": 8,
      "y_mm": 8,
      "width_mm": 281,
      "height_mm": 10,
      "font_size_pt": 16,
      "layer": "title"
    }
  ],
  "exports": {
    "png": true,
    "pdf": false,
    "svg": false
  }
}
